{
    "version": "3",
    "FirstPlayer": "East",
    "Dog": "11-T;07-S;08-S;12-T;05-T;12-C",
    "South": "03-S;02-S;02-T;13-C;07-D;06-D;04-S;05-C;06-T;07-T;14-S;05-D;05-H;20-T;05-S;13-S;01-H;02-C",
    "East": "06-S;06-H;04-C;01-D;09-T;04-H;09-H;03-C;14-D;11-D;08-H;14-H;16-T;19-T;13-T;02-D;09-S;04-T",
    "North": "11-H;01-S;10-H;01-C;00-T;14-T;09-C;03-T;13-H;04-D;10-T;15-T;08-T;11-C;10-D;12-D;01-T;07-H",
    "West": "06-C;21-T;08-C;12-H;10-S;14-C;09-D;13-D;03-H;11-S;10-C;02-H;17-T;18-T;03-D;07-C;08-D;12-S",
    "Fifth": ""
}
